zoort
