Metadata-Version: 1.1
Name: zoort
Version: 0.1.8
Summary: A Python script for automatic MongoDB backups
Home-page: https://github.com/yograterol/zoort
Author: Yohan Graterol
Author-email: y@mejorando.la | yograterol@fedoraproject.org
License: Copyright 2014 Yohan Graterol
